volc_math/__init__.py
volc_math/demo.py
volcano_math-0.0.5.dist-info/LICENSE
volcano_math-0.0.5.dist-info/METADATA
volcano_math-0.0.5.dist-info/WHEEL
volcano_math-0.0.5.dist-info/entry_points.txt
volcano_math-0.0.5.dist-info/top_level.txt
volcano_math-0.0.5.dist-info/RECORD
